en_core_web_sm_vbspacy/__init__.py
en_core_web_sm_vbspacy/meta.json
en_core_web_sm_vbspacy/en_core_web_sm_vbspacy-3.8.0/LICENSE
en_core_web_sm_vbspacy/en_core_web_sm_vbspacy-3.8.0/LICENSES_SOURCES
en_core_web_sm_vbspacy/en_core_web_sm_vbspacy-3.8.0/README.md
en_core_web_sm_vbspacy/en_core_web_sm_vbspacy-3.8.0/accuracy.json
en_core_web_sm_vbspacy/en_core_web_sm_vbspacy-3.8.0/config.cfg
en_core_web_sm_vbspacy/en_core_web_sm_vbspacy-3.8.0/meta.json
en_core_web_sm_vbspacy/en_core_web_sm_vbspacy-3.8.0/tokenizer
en_core_web_sm_vbspacy/en_core_web_sm_vbspacy-3.8.0/attribute_ruler/patterns
en_core_web_sm_vbspacy/en_core_web_sm_vbspacy-3.8.0/lemmatizer/lookups/lookups.bin
en_core_web_sm_vbspacy/en_core_web_sm_vbspacy-3.8.0/ner/cfg
en_core_web_sm_vbspacy/en_core_web_sm_vbspacy-3.8.0/ner/model
en_core_web_sm_vbspacy/en_core_web_sm_vbspacy-3.8.0/ner/moves
en_core_web_sm_vbspacy/en_core_web_sm_vbspacy-3.8.0/parser/cfg
en_core_web_sm_vbspacy/en_core_web_sm_vbspacy-3.8.0/parser/model
en_core_web_sm_vbspacy/en_core_web_sm_vbspacy-3.8.0/parser/moves
en_core_web_sm_vbspacy/en_core_web_sm_vbspacy-3.8.0/senter/cfg
en_core_web_sm_vbspacy/en_core_web_sm_vbspacy-3.8.0/senter/model
en_core_web_sm_vbspacy/en_core_web_sm_vbspacy-3.8.0/tagger/cfg
en_core_web_sm_vbspacy/en_core_web_sm_vbspacy-3.8.0/tagger/model
en_core_web_sm_vbspacy/en_core_web_sm_vbspacy-3.8.0/tok2vec/cfg
en_core_web_sm_vbspacy/en_core_web_sm_vbspacy-3.8.0/tok2vec/model
en_core_web_sm_vbspacy/en_core_web_sm_vbspacy-3.8.0/vocab/key2row
en_core_web_sm_vbspacy/en_core_web_sm_vbspacy-3.8.0/vocab/lookups.bin
en_core_web_sm_vbspacy/en_core_web_sm_vbspacy-3.8.0/vocab/strings.json
en_core_web_sm_vbspacy/en_core_web_sm_vbspacy-3.8.0/vocab/vectors
en_core_web_sm_vbspacy/en_core_web_sm_vbspacy-3.8.0/vocab/vectors.cfg
en_core_web_sm_vbspacy-3.8.0.dist-info/LICENSE
en_core_web_sm_vbspacy-3.8.0.dist-info/LICENSES_SOURCES
en_core_web_sm_vbspacy-3.8.0.dist-info/METADATA
en_core_web_sm_vbspacy-3.8.0.dist-info/WHEEL
en_core_web_sm_vbspacy-3.8.0.dist-info/entry_points.txt
en_core_web_sm_vbspacy-3.8.0.dist-info/top_level.txt
en_core_web_sm_vbspacy-3.8.0.dist-info/RECORD
