Metadata-Version: 2.1
Name: en_core_web_sm_vbspacy
Version: 3.8.0
Summary: Spacy model uploaded to PyPi. All credits go to the original devs.
Home-page: https://explosion.ai
Author: Explosion
Author-email: contact@explosion.ai
License: MIT
License-File: LICENSE
License-File: LICENSES_SOURCES
Requires-Dist: spacy <3.9.0,>=3.7.5
